ordeq_huggingface/__init__.py
ordeq_huggingface/_version.py
ordeq_huggingface/dataset.py
ordeq_huggingface/disk_dataset.py
ordeq_huggingface-1.0.1.dist-info/licenses/LICENSE
ordeq_huggingface-1.0.1.dist-info/METADATA
ordeq_huggingface-1.0.1.dist-info/WHEEL
ordeq_huggingface-1.0.1.dist-info/top_level.txt
ordeq_huggingface-1.0.1.dist-info/RECORD
