Metadata-Version: 2.4
Name: ordeq_huggingface
Version: 1.0.1
Author: Niels Neerhoff, Simon Brugman
Maintainer: Niels Neerhoff, Simon Brugman
License-Expression: MIT
Requires-Python: >=3.10
License-File: LICENSE
Requires-Dist: ordeq>=1.0.0
Requires-Dist: datasets
Dynamic: license-file
